get_field_values_from_config/__init__.py
get_field_values_from_config/get_field_values_from_config.py
get_field_values_from_config-0.0.4.dist-info/METADATA
get_field_values_from_config-0.0.4.dist-info/WHEEL
get_field_values_from_config-0.0.4.dist-info/top_level.txt
get_field_values_from_config-0.0.4.dist-info/RECORD
