Metadata-Version: 2.1
Name: get-field-values-from-config
Version: 0.0.4
Summary: Get field values from config integrationOne
Home-page: https://github.com/pypa/sampleproject
Author: Mr Methane
Author-email: smoothbrain@test.com
Project-URL: Bug Tracker, https://github.com/pypa/sampleproject/issues
Classifier: Programming Language :: Python :: 3
Classifier: License :: OSI Approved :: MIT License
Classifier: Operating System :: OS Independent
Requires-Python: >=3.6
